README.md
setup.py
pulumi_aci/__init__.py
pulumi_aci/_utilities.py
pulumi_aci/provider.py
pulumi_aci/pulumi-plugin.json
pulumi_aci/py.typed
pulumi_aci.egg-info/PKG-INFO
pulumi_aci.egg-info/SOURCES.txt
pulumi_aci.egg-info/dependency_links.txt
pulumi_aci.egg-info/not-zip-safe
pulumi_aci.egg-info/requires.txt
pulumi_aci.egg-info/top_level.txt
pulumi_aci/apic/__init__.py
pulumi_aci/apic/_inputs.py
pulumi_aci/apic/outputs.py
pulumi_aci/apic/rest.py
pulumi_aci/config/__init__.py
pulumi_aci/config/vars.py