Metadata-Version: 2.1
Name: pulumi-aci
Version: 0.0.6
Summary: The Pulumi ACI provider provides resources to interact with a Cisco ACI fabric.
Home-page: https://pulumi.com
License: MPL-2.0
Project-URL: Repository, https://github.com/netascode/pulumi-aci
Keywords: pulumi aci networking cisco
Platform: UNKNOWN
Requires-Python: >=3.7
